{"title":"Strassenverkehrsunfälle und verunfallte Personen",
"subtitle":"Basel-Stadt",
"kuerzel":"I.11.7.5186",
"kuerzelKunde":"GW10",
"description":"Strassenverkehrsunfälle und verunfallte Personen",
"id":5186,
"thema":"11 Verkehr",
"unterthema":"Strassenverkehrsunfälle",
"kennzahlenset":"Nachhaltigkeit",
"raeumlicheGliederung":["Kanton"],
"aktualisierungsdatum":"",
"stufe1":"Bereich Grundbedürfnisse und Wohlergehen",
"stufe2":"Sicherheit",
"stufe3":"",
"stufe4":"",
"stufe5":"", 
"lesehilfe":"Die Verkehrsunfallstatistik 2017 weist nur geringe Abweichungen gegenüber dem Vorjahr auf. Die Zahl der Unfälle lag bei insgesamt 835; die beanzeigte Parkschäden mit pflichtwidrigem Verhalten (unbekannter Schadenverursacher) wurden der besseren Vergleichbarkeit halber herausgefiltert. Insgesamt gab es 446 verunfallte Personen: 360 Leichtverletzte, 85 Schwerverletzte sowie eine Person, welche an den Folgen eines Verkehrsunfalls starb. Dies ist die tiefste Zahl von Verkehrstoten im Kanton Basel-Stadt seit Beginn der Erhebung einer Verkehrsunfallstatistik.",
"erlaeuterungen":"",
"template":"line001",
"darstellungsart":"Grafik",
"printformat":"", 
"visible":true,
"visibleInPortal":true,
"orderKey":"03_04_00_00_00_310",
"parentId":null,
"children":[],
"renderLink":[],
"quellenangabe":["Kantonspolizei Basel-Stadt"],
"datenInChartIntegriert":false,
"externalLinks":[""],
"data-id":5186, 
"chart-id":5186, 
"filter":""
}
