{"title":"Leerwohnungen nach Wohnviertel",
"subtitle":"Stand: 2017",
"kuerzel":"",
"kuerzelKunde":"",
"description":"Leerwohnungen nach Wohnviertel",
"id":6379,
"thema":"01 Bevölkerung",
"unterthema":"",
"kennzahlenset":"PDF_Karten_cont",
"raeumlicheGliederung":["Wohnviertel"],
"aktualisierungsdatum":"",
"schlagwort":["Gebäude"],
"stufe1":"",
"stufe2":"",
"stufe3":"",
"stufe4":"",
"stufe5":"", 
"lesehilfe":"",
"erlaeuterungen":"",
"template":"mappie001",
"option":"options001",
"visible":true,
"visibleInPortal":false,
"orderKey":"_000",
"parentId":null,
"children":["6391"],
"renderLink":["6391"],
"quellenangabe":["Statistisches Amt Basel-Stadt, Leerstandserhebung","Kartengrundlate: Geodaten Kanton Basel-Stadt"],
"externalLinks":[""]
}
