{"title":"Arbeitslose im Dienstleistungssektor (III)",
"subtitle":"2008 bis 2017",
"kuerzel":"I.03.4.06506",
"kuerzelKunde":"3.3-08",
"description":"Arbeitslose im Dienstleistungssektor (III)",
"id":6506,
"thema":"03 Erwerbsleben",
"unterthema":"Arbeitslose ",
"kennzahlenset":"Arbeitsmarkt",
"raeumlicheGliederung":["Kanton"],
"aktualisierungsdatum":"",
"schlagwort":["Arbeitslosigkeit","Branche"],
"stufe1":"Monitoring Basler Arbeitsmarkt",
"stufe2":"Arbeitslosigkeit",
"stufe3":"",
"stufe4":"",
"stufe5":"", 
"lesehilfe":"",
"erlaeuterungen":"Als Arbeitslose gelten Personen, welche bei einem Regionalen Arbeitsvermittlungszentrum (RAV) gemeldet sind, keine Stelle haben und sofort vermittelbar sind.",
"template":"line001",
"visible":false,
"visibleInPortal":true,
"orderKey":"02_03_00_00_00_000",
"parentId":null,
"children":[],
"renderLink":[],
"quellenangabe":["Staatssekretariat für Wirtschaft SECO, Arbeitslosenstatistik"],
"externalLinks":[""]
}
