{"title":"Anzahl Zimmer und Auslastung nach Hotelkategorie",
"subtitle":"Basel-Stadt",
"kuerzel":"I.10.1.6539",
"kuerzelKunde":"2-3",
"description":"Anzahl Zimmer und Auslastung nach Hotelkategorie",
"id":6539,
"thema":"10 Tourismus",
"unterthema":"Hotellerie",
"kennzahlenset":"Tourismus",
"raeumlicheGliederung":["Kanton"],
"aktualisierungsdatum":"2020-12-23T09:46:58.5858",
"stufe1":"Kernindikatoren zum Tourismus",
"stufe2":"",
"stufe3":"",
"stufe4":"",
"stufe5":"", 
"lesehilfe":"2020 standen den Gästen der Basler Hotellerie insgesamt 3 682 Zimmer zur Verfügung. Davon entfielen 1 521 Zimmer auf Betriebe mit 4 oder 5 Sternen, 1 325 auf die Kategorie der 3-Sterne-Hotels und 506 auf die 1- und 2-Sterne-Hotels. 331 Zimmer wurden ohne Klassierung angeboten. Bei den Kategorien der 3-, 4- und 5-Sterne-Hotels fällt die Anzahl verfügbarer Zimmer 2020 unter den Stand von vor zehn Jahren. 2020 nahm die Nettozimmerauslastung gegenüber 2011 in allen Kategorien ab, insgesamt resultiert ein Minus von 31,6%. Am deutlichsten ist die Abnahme bei den 4- und 5-Sterne-Häusern, im Zehnjahresvergleich beläuft sie sich auf 35,4%.",
"erlaeuterungen":"Die Nettozimmerauslastung gibt an, wie oft ein Zimmer an den Tagen belegt war, an denen der Betrieb geöffnet war, und das Zimmer zur Verfügung stand. 2019 wurde die Berechnung der Anzahl verfügbarer Zimmer an die Methodik des BFS angepasst. Für den Jahresvergleich wurde die Berechnung für 2011 rückwirkend angepasst. Die COVID-19-Pandemie und die damit verbundenen Massnahmen zum Schutz der Bevölkerung haben Auswirkungen auf Reiseverhalten und Tourismus.",
"template":"template001",
"darstellungsart":"Diagramm",
"printformat":"", 
"visible":true,
"visibleInPortal":true,
"orderKey":"01_00_00_00_00_003",
"parentId":null,
"children":["7543","7974"],
"renderLink":[],
"quellenangabe":["Statistisches Amt Basel-Stadt, Tourismusstatistik"],
"datenInChartIntegriert":false,
"externalLinks":[""],
"data-id":6539, 
"chart-id":6539, 
"filter":""
}
