{"title":"Anzahl Veranlagungen, Bevölkerung und Summe von Reineinkommen, -vermögen und Steuerertrag",
"subtitle":"indexiert (2006 = 100), Basel-Stadt",
"kuerzel":"I.18.2.06899",
"kuerzelKunde":"2-2",
"description":"Anzahl Veranlagungen, Bevölkerung und Summe von Reineinkommen, -vermögen und Steuerertrag",
"id":6899,
"thema":"18 Öffentliche Finanzen",
"unterthema":"Steuern",
"kennzahlenset":"Steuern",
"raeumlicheGliederung":["Kanton"],
"aktualisierungsdatum":"",
"stufe1":"Ordentliche Veranlagung Natürlicher Personen",
"stufe2":"",
"stufe3":"",
"stufe4":"",
"stufe5":"", 
"lesehilfe":"<bitte Kommentar erfassen>",
"erlaeuterungen":"",
"template":"line001",
"darstellungsart":"",
"printformat":"", 
"visible":true,
"visibleInPortal":true,
"orderKey":"02_00_00_00_00_002",
"parentId":null,
"children":[],
"renderLink":[],
"quellenangabe":["Steuerstatistik Basel-Stadt"],
"externalLinks":[""]
}
