{"title":"Bruttogeschossflächen Wohnen und Arbeiten",
"subtitle":"in m<sup>2</sup>, Basel-Stadt",
"kuerzel":"I.09.1.07774",
"kuerzelKunde":"ST 1-2",
"description":"Bruttogeschossflächen Wohnen und Arbeiten",
"id":7774,
"thema":"09 Bau-, Wohnungswesen",
"unterthema":"Gebäude und Wohnungen",
"kennzahlenset":"Richtplan",
"raeumlicheGliederung":["Kanton"],
"aktualisierungsdatum":"2019-09-05T13:38:52.5252",
"stufe1":"Sachgebiet Querschnittsthemen",
"stufe2":"Strategie 1: Regionale Sichtweise",
"stufe3":"",
"stufe4":"",
"stufe5":"", 
"lesehilfe":"Sowohl beim Wohnen als als auch beim Arbeiten hat die Bruttogeschossfläche seit 1995 zugenommen, was auf die Bautätigkeit im Kanton zurückzuführen ist.",
"erlaeuterungen":"Die Daten zur Bruttogeschossfläche (BGF) werden fünfjährlich aktualisiert, letztmals 2015. Die Bruttogeschossfläche ist die Summer der ober- und unterirdischen Grundflächen von Gebäuden, welche zum Wohnen oder Arbeiten genutzt werden können.",
"template":"line001",
"darstellungsart":"",
"printformat":"", 
"visible":true,
"visibleInPortal":true,
"orderKey":"01_01_00_00_00_012",
"parentId":null,
"children":[],
"renderLink":[],
"quellenangabe":["Bau- und Verkehrsdepartement des Kantons Basel-Stadt"],
"datenInChartIntegriert":false,
"externalLinks":[""],
"data-id":7774, 
"chart-id":7774, 
"filter":""
}
