{"title":"Nettowohnungsproduktion",
"subtitle":"Wohnviertel Rosental",
"kuerzel":"I.09.1.07686",
"kuerzelKunde":"5.08",
"description":"Nettowohnungsproduktion",
"id":8067,
"thema":"09 Bau-, Wohnungswesen",
"unterthema":"Gebäude und Wohnungen",
"kennzahlenset":"Stadtteilmonitoring Klybeck-Kleinhüningen",
"raeumlicheGliederung":["Wohnviertel"],
"aktualisierungsdatum":"2019-11-12T10:01:15.1515",
"stufe1":"5 Bauen und Wohnen",
"stufe2":"",
"stufe3":"",
"stufe4":"",
"stufe5":"", 
"lesehilfe":"<bitte Kommentar erfassen>",
"erlaeuterungen":"Die Nettowohnungsproduktion setzt sich wie folgt zusammen: Neu gebaute Wohnungen minus abgebrochene Wohnungen plus Saldo aus Umbauten (kann positiv oder negativ sein).",
"template":"template001",
"darstellungsart":"Grafik",
"printformat":"", 
"visible":true,
"visibleInPortal":true,
"orderKey":"99_00_00_00_00_008",
"parentId":null,
"children":[],
"renderLink":[],
"quellenangabe":["Statistisches Amt Basel-Stadt, Baustatistik"],
"datenInChartIntegriert":false,
"externalLinks":[""],
"data-id":8067, 
"chart-id":8067, 
"filter":""
}
