{"id":8622,"template":"line001_print","data-id":8622,"chart-id":8622,"filter":"","parentId":"8052","children":[],"title":"Sesshaftigkeit","subtitle":"Wohnviertel Klybeck und Kleinhüningen sowie Stadt Basel","lesehilfe":"In den beiden Wohnvierteln Klybeck und Kleinhüningen liegt der Anteil an Personen, die seit zehn oder mehr Jahren an der gleichen Adresse wohnen, Ende 2024 bei 30,5% bzw. 34,9%. Verglichen mit anderen Wohnvierteln bewegen sich diese Anteile im Mittelfeld. Die Sesshaftigkeit in der Stadt Basel liegt Ende 2024 bei 32,0%.","erlaeuterungen":"Anteil Einwohner, die seit mindestens zehn Jahren an der gleichen Adresse wohnen. Ohne Personen an administrativen Meldeadressen.","quellenangabe":["Statistisches Amt Basel-Stadt, Bevölkerungsstatistik"],"externalLinks":[],"renderLink":[],"raeumlicheGliederung":["Wohnviertel"],"description":"Sesshaftigkeit","thema":"01 Bevölkerung","unterthema":"Bestand und Struktur","kuerzel":"","kennzahlenset":"Stadtteilmonitoring Klybeck-Kleinhüningen (Print)","kuerzelKunde":"2.08","stufe1":"2 Bevölkerung","stufe2":"","stufe3":"","stufe4":"","stufe5":"","orderKey":"02_00_00_00_00_009","darstellungsart":"","printformat":"","visible":true,"visibleInPortal":false,"datenInChartIntegriert":false,"aktualisierungsdatum":"2023-01-02T08:14:10"}
