{
  "series": [
    {
      "color": "#8B2223",
      "index": 12,
      "legendIndex": 0,
      "data": [
        [
          "Innenstadt",
          null
        ],
        [
          "Innenstadt: 2011",
          140
        ],
        [
          "Innenstadt: 2012",
          145
        ],
        [
          "Innenstadt: 2013",
          142
        ],
        [
          "Innenstadt: 2014",
          147
        ],
        [
          "Innenstadt: 2015",
          150
        ],
        [
          "Innenstadt: 2016",
          142
        ],
        [
          "Innenstadt: 2017",
          149
        ],
        [
          "Innenstadt: 2018",
          152
        ],
        [
          "Innenstadt: 2019",
          150
        ],
        [
          " ",
          null
        ],
        [
          "Stadt Basel",
          null
        ],
        [
          "Stadt Basel: 2011",
          641
        ],
        [
          "Stadt Basel: 2012",
          637
        ],
        [
          "Stadt Basel: 2013",
          627
        ],
        [
          "Stadt Basel: 2014",
          646
        ],
        [
          "Stadt Basel: 2015",
          648
        ],
        [
          "Stadt Basel: 2016",
          634
        ],
        [
          "Stadt Basel: 2017",
          638
        ],
        [
          "Stadt Basel: 2018",
          628
        ],
        [
          "Stadt Basel: 2019",
          636
        ]
      ],
      "name": "Primärer Sektor, verarbeit. Gewerbe",
      "turboThreshold": 0
    },
    {
      "color": "#DC440E",
      "index": 11,
      "legendIndex": 1,
      "data": [
        [
          "Innenstadt",
          null
        ],
        [
          "Innenstadt: 2011",
          135
        ],
        [
          "Innenstadt: 2012",
          142
        ],
        [
          "Innenstadt: 2013",
          142
        ],
        [
          "Innenstadt: 2014",
          147
        ],
        [
          "Innenstadt: 2015",
          141
        ],
        [
          "Innenstadt: 2016",
          120
        ],
        [
          "Innenstadt: 2017",
          115
        ],
        [
          "Innenstadt: 2018",
          115
        ],
        [
          "Innenstadt: 2019",
          103
        ],
        [
          " ",
          null
        ],
        [
          "Stadt Basel",
          null
        ],
        [
          "Stadt Basel: 2011",
          1544
        ],
        [
          "Stadt Basel: 2012",
          1560
        ],
        [
          "Stadt Basel: 2013",
          1558
        ],
        [
          "Stadt Basel: 2014",
          1552
        ],
        [
          "Stadt Basel: 2015",
          1530
        ],
        [
          "Stadt Basel: 2016",
          1497
        ],
        [
          "Stadt Basel: 2017",
          1447
        ],
        [
          "Stadt Basel: 2018",
          1418
        ],
        [
          "Stadt Basel: 2019",
          1400
        ]
      ],
      "name": "Bau und Verkehr",
      "turboThreshold": 0
    },
    {
      "color": "#FF8028",
      "index": 10,
      "legendIndex": 2,
      "data": [
        [
          "Innenstadt",
          null
        ],
        [
          "Innenstadt: 2011",
          115
        ],
        [
          "Innenstadt: 2012",
          120
        ],
        [
          "Innenstadt: 2013",
          120
        ],
        [
          "Innenstadt: 2014",
          121
        ],
        [
          "Innenstadt: 2015",
          120
        ],
        [
          "Innenstadt: 2016",
          114
        ],
        [
          "Innenstadt: 2017",
          111
        ],
        [
          "Innenstadt: 2018",
          92
        ],
        [
          "Innenstadt: 2019",
          92
        ],
        [
          " ",
          null
        ],
        [
          "Stadt Basel",
          null
        ],
        [
          "Stadt Basel: 2011",
          501
        ],
        [
          "Stadt Basel: 2012",
          503
        ],
        [
          "Stadt Basel: 2013",
          480
        ],
        [
          "Stadt Basel: 2014",
          483
        ],
        [
          "Stadt Basel: 2015",
          475
        ],
        [
          "Stadt Basel: 2016",
          440
        ],
        [
          "Stadt Basel: 2017",
          412
        ],
        [
          "Stadt Basel: 2018",
          362
        ],
        [
          "Stadt Basel: 2019",
          348
        ]
      ],
      "name": "Grosshandel",
      "turboThreshold": 0
    },
    {
      "color": "#FFBB58",
      "index": 9,
      "legendIndex": 3,
      "data": [
        [
          "Innenstadt",
          null
        ],
        [
          "Innenstadt: 2011",
          691
        ],
        [
          "Innenstadt: 2012",
          675
        ],
        [
          "Innenstadt: 2013",
          673
        ],
        [
          "Innenstadt: 2014",
          654
        ],
        [
          "Innenstadt: 2015",
          648
        ],
        [
          "Innenstadt: 2016",
          628
        ],
        [
          "Innenstadt: 2017",
          615
        ],
        [
          "Innenstadt: 2018",
          600
        ],
        [
          "Innenstadt: 2019",
          592
        ],
        [
          " ",
          null
        ],
        [
          "Stadt Basel",
          null
        ],
        [
          "Stadt Basel: 2011",
          1531
        ],
        [
          "Stadt Basel: 2012",
          1502
        ],
        [
          "Stadt Basel: 2013",
          1473
        ],
        [
          "Stadt Basel: 2014",
          1447
        ],
        [
          "Stadt Basel: 2015",
          1428
        ],
        [
          "Stadt Basel: 2016",
          1391
        ],
        [
          "Stadt Basel: 2017",
          1375
        ],
        [
          "Stadt Basel: 2018",
          1316
        ],
        [
          "Stadt Basel: 2019",
          1282
        ]
      ],
      "name": "Detailhandel",
      "turboThreshold": 0
    },
    {
      "color": "#FFDA80",
      "index": 8,
      "legendIndex": 4,
      "data": [
        [
          "Innenstadt",
          null
        ],
        [
          "Innenstadt: 2011",
          205
        ],
        [
          "Innenstadt: 2012",
          207
        ],
        [
          "Innenstadt: 2013",
          215
        ],
        [
          "Innenstadt: 2014",
          224
        ],
        [
          "Innenstadt: 2015",
          224
        ],
        [
          "Innenstadt: 2016",
          210
        ],
        [
          "Innenstadt: 2017",
          211
        ],
        [
          "Innenstadt: 2018",
          198
        ],
        [
          "Innenstadt: 2019",
          214
        ],
        [
          " ",
          null
        ],
        [
          "Stadt Basel",
          null
        ],
        [
          "Stadt Basel: 2011",
          812
        ],
        [
          "Stadt Basel: 2012",
          842
        ],
        [
          "Stadt Basel: 2013",
          842
        ],
        [
          "Stadt Basel: 2014",
          883
        ],
        [
          "Stadt Basel: 2015",
          878
        ],
        [
          "Stadt Basel: 2016",
          870
        ],
        [
          "Stadt Basel: 2017",
          860
        ],
        [
          "Stadt Basel: 2018",
          852
        ],
        [
          "Stadt Basel: 2019",
          908
        ]
      ],
      "name": "Information, Kommunikation",
      "turboThreshold": 0
    },
    {
      "color": "#007A2F",
      "index": 7,
      "legendIndex": 5,
      "data": [
        [
          "Innenstadt",
          null
        ],
        [
          "Innenstadt: 2011",
          316
        ],
        [
          "Innenstadt: 2012",
          307
        ],
        [
          "Innenstadt: 2013",
          306
        ],
        [
          "Innenstadt: 2014",
          298
        ],
        [
          "Innenstadt: 2015",
          299
        ],
        [
          "Innenstadt: 2016",
          297
        ],
        [
          "Innenstadt: 2017",
          303
        ],
        [
          "Innenstadt: 2018",
          296
        ],
        [
          "Innenstadt: 2019",
          296
        ],
        [
          " ",
          null
        ],
        [
          "Stadt Basel",
          null
        ],
        [
          "Stadt Basel: 2011",
          768
        ],
        [
          "Stadt Basel: 2012",
          771
        ],
        [
          "Stadt Basel: 2013",
          782
        ],
        [
          "Stadt Basel: 2014",
          801
        ],
        [
          "Stadt Basel: 2015",
          799
        ],
        [
          "Stadt Basel: 2016",
          791
        ],
        [
          "Stadt Basel: 2017",
          807
        ],
        [
          "Stadt Basel: 2018",
          786
        ],
        [
          "Stadt Basel: 2019",
          789
        ]
      ],
      "name": "Gastronomie, Hotellerie",
      "turboThreshold": 0
    },
    {
      "color": "#D7E8D2",
      "index": 6,
      "legendIndex": 6,
      "data": [
        [
          "Innenstadt",
          null
        ],
        [
          "Innenstadt: 2011",
          309
        ],
        [
          "Innenstadt: 2012",
          312
        ],
        [
          "Innenstadt: 2013",
          293
        ],
        [
          "Innenstadt: 2014",
          310
        ],
        [
          "Innenstadt: 2015",
          314
        ],
        [
          "Innenstadt: 2016",
          298
        ],
        [
          "Innenstadt: 2017",
          287
        ],
        [
          "Innenstadt: 2018",
          276
        ],
        [
          "Innenstadt: 2019",
          284
        ],
        [
          " ",
          null
        ],
        [
          "Stadt Basel",
          null
        ],
        [
          "Stadt Basel: 2011",
          959
        ],
        [
          "Stadt Basel: 2012",
          983
        ],
        [
          "Stadt Basel: 2013",
          958
        ],
        [
          "Stadt Basel: 2014",
          990
        ],
        [
          "Stadt Basel: 2015",
          964
        ],
        [
          "Stadt Basel: 2016",
          933
        ],
        [
          "Stadt Basel: 2017",
          919
        ],
        [
          "Stadt Basel: 2018",
          890
        ],
        [
          "Stadt Basel: 2019",
          906
        ]
      ],
      "name": "Finanzen, Versicherung, Immobilien",
      "turboThreshold": 0
    },
    {
      "color": "#73BA7C",
      "index": 5,
      "legendIndex": 7,
      "data": [
        [
          "Innenstadt",
          null
        ],
        [
          "Innenstadt: 2011",
          796
        ],
        [
          "Innenstadt: 2012",
          849
        ],
        [
          "Innenstadt: 2013",
          854
        ],
        [
          "Innenstadt: 2014",
          905
        ],
        [
          "Innenstadt: 2015",
          915
        ],
        [
          "Innenstadt: 2016",
          915
        ],
        [
          "Innenstadt: 2017",
          930
        ],
        [
          "Innenstadt: 2018",
          935
        ],
        [
          "Innenstadt: 2019",
          946
        ],
        [
          " ",
          null
        ],
        [
          "Stadt Basel",
          null
        ],
        [
          "Stadt Basel: 2011",
          2702
        ],
        [
          "Stadt Basel: 2012",
          2801
        ],
        [
          "Stadt Basel: 2013",
          2866
        ],
        [
          "Stadt Basel: 2014",
          3096
        ],
        [
          "Stadt Basel: 2015",
          3156
        ],
        [
          "Stadt Basel: 2016",
          3155
        ],
        [
          "Stadt Basel: 2017",
          3176
        ],
        [
          "Stadt Basel: 2018",
          3232
        ],
        [
          "Stadt Basel: 2019",
          3252
        ]
      ],
      "name": "Unternehmens-DL, Freiberufe",
      "turboThreshold": 0
    },
    {
      "color": "#2B0099",
      "index": 4,
      "legendIndex": 8,
      "data": [
        [
          "Innenstadt",
          null
        ],
        [
          "Innenstadt: 2011",
          327
        ],
        [
          "Innenstadt: 2012",
          312
        ],
        [
          "Innenstadt: 2013",
          330
        ],
        [
          "Innenstadt: 2014",
          315
        ],
        [
          "Innenstadt: 2015",
          305
        ],
        [
          "Innenstadt: 2016",
          299
        ],
        [
          "Innenstadt: 2017",
          295
        ],
        [
          "Innenstadt: 2018",
          309
        ],
        [
          "Innenstadt: 2019",
          296
        ],
        [
          " ",
          null
        ],
        [
          "Stadt Basel",
          null
        ],
        [
          "Stadt Basel: 2011",
          1063
        ],
        [
          "Stadt Basel: 2012",
          1041
        ],
        [
          "Stadt Basel: 2013",
          1078
        ],
        [
          "Stadt Basel: 2014",
          1090
        ],
        [
          "Stadt Basel: 2015",
          1061
        ],
        [
          "Stadt Basel: 2016",
          1065
        ],
        [
          "Stadt Basel: 2017",
          1084
        ],
        [
          "Stadt Basel: 2018",
          1101
        ],
        [
          "Stadt Basel: 2019",
          1107
        ]
      ],
      "name": "Sonstige DL",
      "turboThreshold": 0
    },
    {
      "color": "#008AC3",
      "index": 3,
      "legendIndex": 9,
      "data": [
        [
          "Innenstadt",
          null
        ],
        [
          "Innenstadt: 2011",
          229
        ],
        [
          "Innenstadt: 2012",
          226
        ],
        [
          "Innenstadt: 2013",
          231
        ],
        [
          "Innenstadt: 2014",
          233
        ],
        [
          "Innenstadt: 2015",
          240
        ],
        [
          "Innenstadt: 2016",
          246
        ],
        [
          "Innenstadt: 2017",
          245
        ],
        [
          "Innenstadt: 2018",
          244
        ],
        [
          "Innenstadt: 2019",
          253
        ],
        [
          " ",
          null
        ],
        [
          "Stadt Basel",
          null
        ],
        [
          "Stadt Basel: 2011",
          857
        ],
        [
          "Stadt Basel: 2012",
          870
        ],
        [
          "Stadt Basel: 2013",
          875
        ],
        [
          "Stadt Basel: 2014",
          896
        ],
        [
          "Stadt Basel: 2015",
          921
        ],
        [
          "Stadt Basel: 2016",
          917
        ],
        [
          "Stadt Basel: 2017",
          920
        ],
        [
          "Stadt Basel: 2018",
          924
        ],
        [
          "Stadt Basel: 2019",
          982
        ]
      ],
      "name": "Öff. Verwaltung, Bildung",
      "turboThreshold": 0
    },
    {
      "color": "#B9CFD7",
      "index": 2,
      "legendIndex": 10,
      "data": [
        [
          "Innenstadt",
          null
        ],
        [
          "Innenstadt: 2011",
          597
        ],
        [
          "Innenstadt: 2012",
          610
        ],
        [
          "Innenstadt: 2013",
          609
        ],
        [
          "Innenstadt: 2014",
          626
        ],
        [
          "Innenstadt: 2015",
          657
        ],
        [
          "Innenstadt: 2016",
          683
        ],
        [
          "Innenstadt: 2017",
          698
        ],
        [
          "Innenstadt: 2018",
          714
        ],
        [
          "Innenstadt: 2019",
          710
        ],
        [
          " ",
          null
        ],
        [
          "Stadt Basel",
          null
        ],
        [
          "Stadt Basel: 2011",
          2071
        ],
        [
          "Stadt Basel: 2012",
          2116
        ],
        [
          "Stadt Basel: 2013",
          2149
        ],
        [
          "Stadt Basel: 2014",
          2247
        ],
        [
          "Stadt Basel: 2015",
          2316
        ],
        [
          "Stadt Basel: 2016",
          2345
        ],
        [
          "Stadt Basel: 2017",
          2362
        ],
        [
          "Stadt Basel: 2018",
          2362
        ],
        [
          "Stadt Basel: 2019",
          2423
        ]
      ],
      "name": "Gesundheits-, Sozialwesen",
      "turboThreshold": 0
    },
    {
      "color": "#672773",
      "index": 1,
      "legendIndex": 11,
      "data": [
        [
          "Innenstadt",
          null
        ],
        [
          "Innenstadt: 2011",
          183
        ],
        [
          "Innenstadt: 2012",
          195
        ],
        [
          "Innenstadt: 2013",
          205
        ],
        [
          "Innenstadt: 2014",
          210
        ],
        [
          "Innenstadt: 2015",
          217
        ],
        [
          "Innenstadt: 2016",
          207
        ],
        [
          "Innenstadt: 2017",
          213
        ],
        [
          "Innenstadt: 2018",
          205
        ],
        [
          "Innenstadt: 2019",
          203
        ],
        [
          " ",
          null
        ],
        [
          "Stadt Basel",
          null
        ],
        [
          "Stadt Basel: 2011",
          993
        ],
        [
          "Stadt Basel: 2012",
          1050
        ],
        [
          "Stadt Basel: 2013",
          1090
        ],
        [
          "Stadt Basel: 2014",
          1221
        ],
        [
          "Stadt Basel: 2015",
          1288
        ],
        [
          "Stadt Basel: 2016",
          1270
        ],
        [
          "Stadt Basel: 2017",
          1246
        ],
        [
          "Stadt Basel: 2018",
          1241
        ],
        [
          "Stadt Basel: 2019",
          1256
        ]
      ],
      "name": "Kunst, Unterhaltung, Sport",
      "turboThreshold": 0
    },
    {
      "color": "#E7CEE2",
      "index": 0,
      "legendIndex": 12,
      "data": [
        [
          "Innenstadt",
          null
        ],
        [
          "Innenstadt: 2011",
          288
        ],
        [
          "Innenstadt: 2012",
          305
        ],
        [
          "Innenstadt: 2013",
          323
        ],
        [
          "Innenstadt: 2014",
          319
        ],
        [
          "Innenstadt: 2015",
          328
        ],
        [
          "Innenstadt: 2016",
          335
        ],
        [
          "Innenstadt: 2017",
          335
        ],
        [
          "Innenstadt: 2018",
          332
        ],
        [
          "Innenstadt: 2019",
          340
        ],
        [
          " ",
          null
        ],
        [
          "Stadt Basel",
          null
        ],
        [
          "Stadt Basel: 2011",
          824
        ],
        [
          "Stadt Basel: 2012",
          831
        ],
        [
          "Stadt Basel: 2013",
          865
        ],
        [
          "Stadt Basel: 2014",
          884
        ],
        [
          "Stadt Basel: 2015",
          888
        ],
        [
          "Stadt Basel: 2016",
          893
        ],
        [
          "Stadt Basel: 2017",
          891
        ],
        [
          "Stadt Basel: 2018",
          879
        ],
        [
          "Stadt Basel: 2019",
          914
        ]
      ],
      "name": "Schönheitspflege, sonst. pers. DL",
      "turboThreshold": 0
    }
  ],
  "xAxis": {
    "type": "category",
    "uniqueNames": true,
    "lineColor": "#B9CFD7",
    "lineWidth": 0.5,
    "tickLength": 0,
    "title": {
      "style": {
        "color": "#000000"
      }
    },
    "labels": {
      "style": {
        "color": "#000000"
      },
      "formatter": function () {
              //add sum of observations of visible series to the axis label
              var allVisibleSeries = this.chart.series.filter(function (val, i, arr) {
                  return val.visible;
              });
              var indexOfCurrentValue = this.axis.names.indexOf(this.value);
              var sum = allVisibleSeries.reduce(function (accumulator, series, index, arr) {
                  return accumulator + series.yData[indexOfCurrentValue];
              }, 0);
              //use N if all series are visible, otherwise use n
              var nString = /*(this.chart.series.length == allVisibleSeries.length) ? 'N=' : */'n=';

              //delete everything before ":", including ":"
              this.value = this.value.replace(/[^:]*:/, "");

              //check for value that contains only spaces
              if (sum != 0) return (this.value.replace(/\s/g, "") == "") ? this.value : this.value;
              //else, if sum = 0, then it is assumed to be an intermediate title. return it bold
              return "<b>" + this.value + "</b>";
          }
    }
  },
  "chart": {
    "width": 485,
    "height": 428,
    "spacing": [
      10,
      10,
      30,
      10
    ],
    "borderColor": "#fbfbfb",
    "backgroundColor": "#fbfbfb",
    "style": {
      "fontFamily": "Arial"
    },
    "zoomType": "xy",
    "panning": true,
    "panKey": "shift",
    "events": {
      "load": function () {
                    this.credits.element.onclick = function () { };

                    //for top-left legends with no x defined: move legend to x position of first yAxis
                    if (this['legend']['options']['align'] == 'left' && this['legend']['options']['verticalAlign'] == 'top' && this['legend']['options']['x'] == 0) {
                        this.update(
                            {
                                legend: {
                                    x: this.yAxis[0].left - this.spacingBox.x - this.legend.padding
                                }
                            }
                        );
                    }
                }
    },
    "type": "column",
    "renderTo": "container-9575",
    "spacingBottom": 40
  },
  "plotOptions": {
    "series": {
      "borderWidth": 0,
      "dataLabels": {
        "style": {
          "fontSize": "10px"
        }
      },
      "stacking": "percent",
      "groupPadding": 0
    }
  },
  "title": {
    "align": "left",
    "style": {
      "fontSize": "14px",
      "fontWeight": "bold",
      "color": "#000000"
    },
    "text": "Arbeitsstätten nach Branche"
  },
  "subtitle": {
    "text": "Innenstadt und Stadt Basel",
    "align": "left",
    "style": {
      "fontSize": "12px",
      "fontWeight": "normal",
      "color": "#000000"
    }
  },
  "yAxis": {
    "gridLineWidth": 0.5,
    "gridLineColor": "#B9CFD7",
    "lineColor": "#B9CFD7",
    "title": {
      "style": {
        "color": "#000000",
        "fontSize": null
      },
      "text": null
    },
    "labels": {
      "style": {
        "color": "#000000"
      },
      "format": "{value:,.0f}%"
    },
    "tickAmount": 6
  },
  "legend": {
    "symbolRadius": 0,
    "itemStyle": {
      "fontWeight": "normal"
    },
    "enabled": true,
    "reversed": false,
    "layout": "horizontal",
    "verticalAlign": "top",
    "align": "left",
    "padding": 0,
    "itemDistance": 2,
    "width": 500,
    "itemWidth": 230,
    "itemMarginBottom": 1
  },
  "navigation": {
    "menuItemStyle": {
      "fontFamily": "\"Lucida Grande\", \"Lucida Sans Unicode\", Arial, Helvetica, sans-serif",
      "padding": "2px 10px"
    }
  },
  "credits": {
    "enabled": true,
    "style": {
      "color": "#000000",
      "fontSize": "10px",
      "cursor": "default"
    },
    "position": {
      "align": "left",
      "verticalAlign": "bottom",
      "x": 10,
      "y": -25
    },
    "text": "Quelle: Bundesamt für Statistik (BFS), Statistik der Unternehmensstruktur (STATENT).\u003Cbr\u002F\u003EZuletzt geändert: 11.7.2022"
  },
  "tooltip": {
    "pointFormat": "\u003Cspan style=\"color:{point.color}\"\u003E●\u003C\u002Fspan\u003E {series.name}: \u003Cb\u003E{point.y:,.0f}\u003C\u002Fb\u003E ({point.percentage:.1f}%)\u003Cbr\u002F\u003E",
    "footerFormat": "Total: \u003Cb\u003E{point.total:,.0f}\u003C\u002Fb\u003E",
    "shared": true
  },
  "exporting": {
    "filename": "9575"
  }
}